seismometer/__init__.py
seismometer/seismogram.py
seismometer/api/__init__.py
seismometer/api/explore.py
seismometer/api/plots.py
seismometer/api/reports.py
seismometer/api/templates.py
seismometer/api/utils.py
seismometer/configuration/__init__.py
seismometer/configuration/config.py
seismometer/configuration/config_helpers.py
seismometer/configuration/export_config.py
seismometer/configuration/metrics.py
seismometer/configuration/model.py
seismometer/controls/categorical.py
seismometer/controls/categorical_single_column.py
seismometer/controls/cohort_comparison.py
seismometer/controls/decorators.py
seismometer/controls/explore.py
seismometer/controls/selection.py
seismometer/controls/styles.py
seismometer/controls/thresholds.py
seismometer/core/autometrics.py
seismometer/core/decorators.py
seismometer/core/exceptions.py
seismometer/core/io.py
seismometer/core/logger.py
seismometer/core/patterns.py
seismometer/data/__init__.py
seismometer/data/binary_performance.py
seismometer/data/cohorts.py
seismometer/data/decorators.py
seismometer/data/filter.py
seismometer/data/metric_apis.py
seismometer/data/otel.py
seismometer/data/pandas_helpers.py
seismometer/data/performance.py
seismometer/data/summaries.py
seismometer/data/timeseries.py
seismometer/data/confidence/__init__.py
seismometer/data/confidence/calculations.py
seismometer/data/confidence/parameters.py
seismometer/data/loader/__init__.py
seismometer/data/loader/event.py
seismometer/data/loader/pipeline.py
seismometer/data/loader/prediction.py
seismometer/html/template.py
seismometer/html/resources/cohorts.html
seismometer/html/resources/info.html
seismometer/html/resources/title_image.html
seismometer/html/resources/title_message.html
seismometer/plot/__init__.py
seismometer/plot/mpl/__init__.py
seismometer/plot/mpl/_lines.py
seismometer/plot/mpl/_util.py
seismometer/plot/mpl/_ux.py
seismometer/plot/mpl/binary_classifier.py
seismometer/plot/mpl/decorators.py
seismometer/plot/mpl/likert.py
seismometer-0.5.0.dist-info/licenses/LICENSE.txt
seismometer-0.5.0.dist-info/METADATA
seismometer-0.5.0.dist-info/WHEEL
seismometer-0.5.0.dist-info/top_level.txt
seismometer-0.5.0.dist-info/zip-safe
seismometer-0.5.0.dist-info/RECORD
