Metadata-Version: 2.4
Name: seismometer
Version: 0.5.0
Summary: seismometer: Data Science visualization and investigation tools for AI Trust & Assurance
Author: Epic
Author-email: OpenSourceContributions-Python@epic.com
License: BSD-3-Clause
Project-URL: Source, https://github.com/epic-open-source/seismometer
Classifier: Programming Language :: Python :: 3
Classifier: Operating System :: OS Independent
Classifier: Intended Audience :: Healthcare Industry
Classifier: Framework :: Jupyter :: JupyterLab :: 4
Requires-Python: >=3.10
License-File: LICENSE.txt
Requires-Dist: numpy<3,>=1.26
Requires-Dist: ipython>=8.14
Requires-Dist: ipywidgets>=8.0
Requires-Dist: jupyterlab<5,>=4.2.5
Requires-Dist: matplotlib<4,>=3.6
Requires-Dist: seaborn<0.14,>=0.13.2
Requires-Dist: pandas<3,>=2.1
Requires-Dist: scikit-learn<2,>=1.2.0
Requires-Dist: pyarrow<20.0.0,>14.0.0
Requires-Dist: pydantic<3,>=2.6.3
Requires-Dist: ydata-profiling<5,>=4.8.3
Requires-Dist: great-tables<1,>=0.11.0
Provides-Extra: all
Requires-Dist: coverage>=7.5.1; extra == "all"
Requires-Dist: autopep8>=1.3.5; extra == "all"
Requires-Dist: pytest-json>=0.4.0; extra == "all"
Requires-Dist: pytest>=5.1.1; extra == "all"
Requires-Dist: traitlets>=5.1.1; extra == "all"
Requires-Dist: pygments>=2.4.1; extra == "all"
Requires-Dist: sphinx>=7.2.6; extra == "all"
Requires-Dist: sphinxawesome-theme>=5.0.0; extra == "all"
Requires-Dist: docutils>=0.20.1; extra == "all"
Requires-Dist: nbsphinx>=0.9.0; extra == "all"
Requires-Dist: nbsphinx_link>=1.0.0; extra == "all"
Requires-Dist: autodoc_pydantic>=2.0.0; extra == "all"
Requires-Dist: sphinx_design>=0.5.0; extra == "all"
Requires-Dist: sphinx-argparse<0.5.0,>=0.4.0; extra == "all"
Requires-Dist: erdantic>=1.0.0; extra == "all"
Requires-Dist: pandoc>=2.0; extra == "all"
Requires-Dist: opentelemetry-sdk>=1.34.1; extra == "all"
Requires-Dist: opentelemetry-exporter-otlp>=1.34.1; extra == "all"
Provides-Extra: dev
Requires-Dist: coverage>=7.5.1; extra == "dev"
Requires-Dist: autopep8>=1.3.5; extra == "dev"
Requires-Dist: pytest-json>=0.4.0; extra == "dev"
Requires-Dist: pytest>=5.1.1; extra == "dev"
Requires-Dist: traitlets>=5.1.1; extra == "dev"
Requires-Dist: pygments>=2.4.1; extra == "dev"
Provides-Extra: docs
Requires-Dist: sphinx>=7.2.6; extra == "docs"
Requires-Dist: sphinxawesome-theme>=5.0.0; extra == "docs"
Requires-Dist: docutils>=0.20.1; extra == "docs"
Requires-Dist: nbsphinx>=0.9.0; extra == "docs"
Requires-Dist: nbsphinx_link>=1.0.0; extra == "docs"
Requires-Dist: autodoc_pydantic>=2.0.0; extra == "docs"
Requires-Dist: sphinx_design>=0.5.0; extra == "docs"
Requires-Dist: sphinx-argparse<0.5.0,>=0.4.0; extra == "docs"
Requires-Dist: erdantic>=1.0.0; extra == "docs"
Requires-Dist: pandoc>=2.0; extra == "docs"
Provides-Extra: metrics
Requires-Dist: opentelemetry-sdk>=1.34.1; extra == "metrics"
Requires-Dist: opentelemetry-exporter-otlp>=1.34.1; extra == "metrics"
Dynamic: license-file
